pylathedb/__init__.py
pylathedb/lathe.py
pylathedb/candidate_network/__init__.py
pylathedb/candidate_network/candidate_network.py
pylathedb/candidate_network/candidate_network_handler.py
pylathedb/database/__init__.py
pylathedb/database/database_handler.py
pylathedb/database/database_iter.py
pylathedb/evaluation/__init__.py
pylathedb/evaluation/evaluation_handler.py
pylathedb/evaluation/evaluation_result.py
pylathedb/index/__init__.py
pylathedb/index/babel_hash.py
pylathedb/index/index_handler.py
pylathedb/index/schema_graph.py
pylathedb/index/schema_index.py
pylathedb/index/value_index.py
pylathedb/keyword_match/__init__.py
pylathedb/keyword_match/keyword_match.py
pylathedb/keyword_match/keyword_match_handler.py
pylathedb/query_match/__init__.py
pylathedb/query_match/query_match.py
pylathedb/query_match/query_match_handler.py
pylathedb/utils/__init__.py
pylathedb/utils/config_handler.py
pylathedb/utils/graph.py
pylathedb/utils/lathe_result.py
pylathedb/utils/logger.py
pylathedb/utils/memory.py
pylathedb/utils/next_path.py
pylathedb/utils/ordinal.py
pylathedb/utils/plots.py
pylathedb/utils/printmd.py
pylathedb/utils/shift_tab.py
pylathedb/utils/similarity.py
pylathedb/utils/tf_iaf.py
pylathedb/utils/timestr.py
pylathedb/utils/tokenizer.py
pylathedb/utils/truncate.py
pylathedb-1.0.9.dist-info/LICENSE
pylathedb-1.0.9.dist-info/METADATA
pylathedb-1.0.9.dist-info/WHEEL
pylathedb-1.0.9.dist-info/top_level.txt
pylathedb-1.0.9.dist-info/RECORD
