Metadata-Version: 2.1
Name: pylathedb
Version: 1.0.9
Summary: Keyword Search over Relational Databases
Home-page: https://github.com/pr3martins/PyLatheDB
Author: Paulo Martins
Author-email: paulo.martins@icomp.ufam.edu.br
Project-URL: Bug Tracker, https://github.com/pr3martins/PyLatheDB/issues
Classifier: Programming Language :: Python :: 3
Classifier: License :: OSI Approved :: GNU General Public License v3 (GPLv3)
Classifier: Operating System :: OS Independent
Requires-Python: >=3.6
License-File: LICENSE
Requires-Dist: nltk
Requires-Dist: psutil
Requires-Dist: psycopg2-binary
Requires-Dist: matplotlib
Requires-Dist: prettytable
Requires-Dist: pandas
Requires-Dist: graphviz
